dice_apply/__init__.py
dice_apply/__main__.py
dice_apply/cli.py
dice_apply/core.py
dice_apply-0.1.2.dist-info/LICENSE
dice_apply-0.1.2.dist-info/METADATA
dice_apply-0.1.2.dist-info/WHEEL
dice_apply-0.1.2.dist-info/entry_points.txt
dice_apply-0.1.2.dist-info/top_level.txt
dice_apply-0.1.2.dist-info/RECORD
