Metadata-Version: 2.1
Name: dice-apply
Version: 0.1.2
Summary: Automated job application tool for Dice.com
Author-email: Sam Savage <samatcrispy@gmail.com>
License: MIT
Project-URL: Homepage, https://github.com/samsavage/robo-apply
Project-URL: Repository, https://github.com/samsavage/robo-apply
Project-URL: Issues, https://github.com/samsavage/robo-apply/issues
Keywords: dice,job,application,automation,selenium,career
Classifier: Development Status :: 4 - Beta
Classifier: Intended Audience :: Developers
Classifier: License :: OSI Approved :: MIT License
Classifier: Operating System :: OS Independent
Classifier: Programming Language :: Python :: 3
Classifier: Programming Language :: Python :: 3.8
Classifier: Programming Language :: Python :: 3.9
Classifier: Programming Language :: Python :: 3.10
Classifier: Programming Language :: Python :: 3.11
Classifier: Programming Language :: Python :: 3.12
Classifier: Topic :: Internet :: WWW/HTTP :: Browsers
Classifier: Topic :: Office/Business
Classifier: Topic :: Software Development :: Libraries :: Python Modules
Requires-Python: >=3.8
License-File: LICENSE
Requires-Dist: selenium >=4.0.0
Requires-Dist: webdriver-manager >=3.8.0
Requires-Dist: requests >=2.25.0
Provides-Extra: dev
Requires-Dist: pytest >=6.0 ; extra == 'dev'
Requires-Dist: black ; extra == 'dev'
Requires-Dist: flake8 ; extra == 'dev'
Requires-Dist: mypy ; extra == 'dev'
